LICENSE
MANIFEST.in
README.md
pyproject.toml
src/pystart/README.md
src/pystart/VERSION
src/pystart/__init__.py
src/pystart/__main__.py
src/pystart/assistance.py
src/pystart/ast_utils.py
src/pystart/backend.py
src/pystart/base_file_browser.py
src/pystart/codeview.py
src/pystart/common.py
src/pystart/compile_po.py
src/pystart/config.py
src/pystart/config_ui.py
src/pystart/custom_notebook.py
src/pystart/defaults.ini
src/pystart/dnd.py
src/pystart/editor_helpers.py
src/pystart/editors.py
src/pystart/export.py
src/pystart/first_run.py
src/pystart/gridtable.py
src/pystart/languages.py
src/pystart/lsp_proxy.py
src/pystart/lsp_types.py
src/pystart/main.py
src/pystart/memory.py
src/pystart/misc_utils.py
src/pystart/program_analysis.py
src/pystart/resize_icons.py
src/pystart/roughparse.py
src/pystart/rst_utils.py
src/pystart/running.py
src/pystart/shell.py
src/pystart/terminal.py
src/pystart/tktextext.py
src/pystart/token_utils.py
src/pystart/udisks.py
src/pystart/ui_utils.py
src/pystart/venv_dialog.py
src/pystart/workbench.py
src/pystart/workdlg.py
src/pystart/locale/compile_mo.bat
src/pystart/locale/pystart.pot
src/pystart/locale/register_updates.py
src/pystart/locale/update_pot.bat
src/pystart/locale/ar_AR/LC_MESSAGES/pystart.mo
src/pystart/locale/ar_AR/LC_MESSAGES/pystart.po
src/pystart/locale/ar_AR/LC_MESSAGES/registered.json
src/pystart/locale/be_BY/LC_MESSAGES/pystart.mo
src/pystart/locale/be_BY/LC_MESSAGES/pystart.po
src/pystart/locale/be_BY/LC_MESSAGES/registered.json
src/pystart/locale/ca_ES/LC_MESSAGES/pystart.mo
src/pystart/locale/ca_ES/LC_MESSAGES/pystart.po
src/pystart/locale/ca_ES/LC_MESSAGES/registered.json
src/pystart/locale/cs_CZ/LC_MESSAGES/pystart.mo
src/pystart/locale/cs_CZ/LC_MESSAGES/pystart.po
src/pystart/locale/cs_CZ/LC_MESSAGES/registered.json
src/pystart/locale/de_DE/LC_MESSAGES/pystart.mo
src/pystart/locale/de_DE/LC_MESSAGES/pystart.po
src/pystart/locale/de_DE/LC_MESSAGES/registered.json
src/pystart/locale/el_GR/LC_MESSAGES/pystart.mo
src/pystart/vendored_libs/circuitpython-typeshed/circuitpython_typeshed-0.1.0.dist-info/INSTALLER
src/pystart/vendored_libs/circuitpython-typeshed/circuitpython_typeshed-0.1.0.dist-info/METADATA
src/pystart/vendored_libs/circuitpython-typeshed/circuitpython_typeshed-0.1.0.dist-info/RECORD
src/pystart/vendored_libs/circuitpython-typeshed/circuitpython_typeshed-0.1.0.dist-info/REQUESTED
src/pystart/vendored_libs/circuitpython-typeshed/circuitpython_typeshed-0.1.0.dist-info/WHEEL
src/pystart/vendored_libs/circuitpython-typeshed/circuitpython_typeshed-0.1.0.dist-info/entry_points.txt
src/pystart/vendored_libs/circuitpython-typeshed/circuitpython_typeshed-0.1.0.dist-info/top_level.txt
src/pystart/vendored_libs/circuitpython-typeshed/circuitpython_typeshed-0.1.0.dist-info/licenses/LICENSE
src/pystart/vendored_libs/micropython-simplified-typeshed/micropython_microbit_stubs_en-0.0.1b2.dist-info/INSTALLER
src/pystart/vendored_libs/micropython-simplified-typeshed/micropython_microbit_stubs_en-0.0.1b2.dist-info/METADATA
src/pystart/vendored_libs/micropython-simplified-typeshed/micropython_microbit_stubs_en-0.0.1b2.dist-info/RECORD
src/pystart/vendored_libs/micropython-simplified-typeshed/micropython_microbit_stubs_en-0.0.1b2.dist-info/REQUESTED
src/pystart/vendored_libs/micropython-simplified-typeshed/micropython_microbit_stubs_en-0.0.1b2.dist-info/WHEEL
src/pystart/vendored_libs/micropython-simplified-typeshed/micropython_microbit_stubs_en-0.0.1b2.dist-info/top_level.txt
src/pystart/vendored_libs/micropython-simplified-typeshed/micropython_microbit_stubs_en-0.0.1b2.dist-info/licenses/LICENSE.md
src/pystart/vendored_libs/micropython-typeshed/micropython_typeshed-0.1.0.dist-info/INSTALLER
src/pystart/vendored_libs/micropython-typeshed/micropython_typeshed-0.1.0.dist-info/METADATA
src/pystart/vendored_libs/micropython-typeshed/micropython_typeshed-0.1.0.dist-info/RECORD
src/pystart/vendored_libs/micropython-typeshed/micropython_typeshed-0.1.0.dist-info/REQUESTED
src/pystart/vendored_libs/micropython-typeshed/micropython_typeshed-0.1.0.dist-info/WHEEL
src/pystart/vendored_libs/micropython-typeshed/micropython_typeshed-0.1.0.dist-info/top_level.txt
src/pystart/vendored_libs/micropython-typeshed/micropython_typeshed-0.1.0.dist-info/licenses/LICENSE
src/pystart/vendored_libs/micropython-unix-typeshed/micropython_stdlib_stubs-1.25.0.dist-info/INSTALLER
src/pystart/vendored_libs/micropython-unix-typeshed/micropython_stdlib_stubs-1.25.0.dist-info/METADATA
src/pystart/vendored_libs/micropython-unix-typeshed/micropython_stdlib_stubs-1.25.0.dist-info/RECORD
src/pystart/vendored_libs/micropython-unix-typeshed/micropython_stdlib_stubs-1.25.0.dist-info/WHEEL
src/pystart/vendored_libs/micropython-unix-typeshed/micropython_stdlib_stubs-1.25.0.dist-info/licenses/LICENSE.md
src/pystart/vendored_libs/micropython-unix-typeshed/micropython_stdlib_stubs-1.25.0.dist-info/licenses/LICENSE_typeshed
src/pystart/vendored_libs/micropython-unix-typeshed/micropython_unix_stubs-1.24.1.post2.dist-info/INSTALLER
src/pystart/vendored_libs/micropython-unix-typeshed/micropython_unix_stubs-1.24.1.post2.dist-info/LICENSE.md
src/pystart/vendored_libs/micropython-unix-typeshed/micropython_unix_stubs-1.24.1.post2.dist-info/METADATA
src/pystart/vendored_libs/micropython-unix-typeshed/micropython_unix_stubs-1.24.1.post2.dist-info/RECORD
src/pystart/vendored_libs/micropython-unix-typeshed/micropython_unix_stubs-1.24.1.post2.dist-info/REQUESTED
src/pystart/vendored_libs/micropython-unix-typeshed/micropython_unix_stubs-1.24.1.post2.dist-info/WHEEL
src/pystart_ide.egg-info/PKG-INFO
src/pystart_ide.egg-info/SOURCES.txt
src/pystart_ide.egg-info/dependency_links.txt
src/pystart_ide.egg-info/entry_points.txt
src/pystart_ide.egg-info/requires.txt
src/pystart_ide.egg-info/top_level.txt