Metadata-Version: 2.4
Name: pystart-ide
Version: 2.1.2
Summary: PyStart IDE - A beginner-friendly Python IDE for learning and exploration
Author-email: Liu Yang <outcrop@gmail.com>
Maintainer-email: Liu Yang <outcrop@gmail.com>
License: MIT
Project-URL: Homepage, https://github.com/AEKnow/PyStart
Project-URL: Documentation, https://github.com/AEKnow/PyStart/wiki
Project-URL: Repository, https://github.com/AEKnow/PyStart
Project-URL: Issues, https://github.com/AEKnow/PyStart/issues
Keywords: IDE,Python,education,beginner,learning,programming
Classifier: Development Status :: 5 - Production/Stable
Classifier: Environment :: MacOS X
Classifier: Environment :: Win32 (MS Windows)
Classifier: Environment :: X11 Applications
Classifier: Intended Audience :: Developers
Classifier: Intended Audience :: Education
Classifier: Intended Audience :: End Users/Desktop
Classifier: License :: Freeware
Classifier: License :: OSI Approved :: MIT License
Classifier: Natural Language :: Chinese (Simplified)
Classifier: Natural Language :: English
Classifier: Operating System :: MacOS
Classifier: Operating System :: Microsoft :: Windows
Classifier: Operating System :: POSIX :: Linux
Classifier: Programming Language :: Python
Classifier: Programming Language :: Python :: 3
Classifier: Programming Language :: Python :: 3.9
Classifier: Programming Language :: Python :: 3.10
Classifier: Programming Language :: Python :: 3.11
Classifier: Programming Language :: Python :: 3.12
Classifier: Programming Language :: Python :: 3.13
Classifier: Topic :: Education
Classifier: Topic :: Software Development
Classifier: Topic :: Software Development :: Debuggers
Classifier: Topic :: Text Editors :: Integrated Development Environments (IDE)
Requires-Python: >=3.9
License-File: LICENSE
Requires-Dist: jedi>=0.18.1
Requires-Dist: pyserial>=3.4
Requires-Dist: docutils>=0.16
Requires-Dist: asttokens>=2.0
Requires-Dist: Send2Trash>=1.5
Requires-Dist: setuptools>=45.2
Requires-Dist: wheel
Requires-Dist: openai>=1.0.0
Provides-Extra: dev
Requires-Dist: pytest; extra == "dev"
Requires-Dist: black; extra == "dev"
Requires-Dist: isort; extra == "dev"
Dynamic: license-file
